Workbook

Sheet CPSC_VSL_Guidance
A1: Data Year | B1: Agency | C1: VSL_USD2022
A2: 2024 | B2: EPA | C2: 11 | E2: Source | F2: https://www.federalregister.gov/documents/2024/04/18/2024-08300/notice-of-availability-of-final-guidance-for-estimating-value-per-statistical-life
A3: 2024 | B3: DOT | C3: 12.5 | E3: Citation | F3: Consumer Product Safety Commission (CPSC) 2024 Notice of Availability of Final Guidance for Estimating Value per Statistical Life Fed. Regist. Online: https://www.federalregister.gov/documents/2024/04/18/2024-08300/notice-of-availability-of-final-guidance-for-estimating-value-per-statistical-life
A4: 2024 | B4: HHS | C4: 12.3

Sheet CBO_Table_C1
A1: This file presents the data from the tables and figures in CBO’s June 2023 report The 2023 Long-Term Budget Outlook.
A2: www.cbo.gov/publication/59014
A5: Table C-1. Average Annual Values for Additional Economic Variables That Underlie CBO’s Extended Baseline Projections
A6: Percent
B8: 1993–2022 | C8: 2023–2033 | D8: 2034–2043 | E8: 2044–2053 | F8: Overall, 2023–2053
A9: Unemployment
A10: Unemployment rate | B10: 5.747 | C10: 4.582 | D10: 4.327 | E10: 4.139 | F10: 4.357
A11: Noncyclical Rate of Unemployment | B11: 4.939 | C11: 4.34 | D11: 4.099 | E11: 3.934 | F11: 4.131
A12: Growth of Average Weekly Hours Worked | B12: -0.038 | C12: 0.029 | D12: -0.017 | E12: -0.017 | F12: 0
A13: Growth of Total Hours Worked | B13: 0.897 | C13: 0.451 | D13: 0.285 | E13: 0.214 | F13: 0.321
A14: Earnings as a Share of Compensation | B14: 81.312 | C14: 81.838 | D14: 80.897 | E14: 80.123 | F14: 80.981
A15: Growth of Real Earnings per Worker | B15: 1.127 | C15: 1.158 | D15: 0.938 | E15: 0.965 | F15: 1.025
A16: Growth of Total Factor Productivity | B16: 1.192 | C16: 1.116 | D16: 1.092 | E16: 1.093 | F16: 1.101
A17: Growth of Labor Productivity (Real GDP per hour worked) | B17: 1.531 | C17: 1.409 | D17: 1.314 | E17: 1.286 | F17: 1.339
A20: Back to Table of Contents

Sheet CPSC_HHS_VSL_Guidelines
A1: cbo_real_growth_rate | B1: income_elasticity | C1: cpi_ratio_2023_2022
A2: =ROUND(CBO_Table_C1!$F$15,1) -> 1 | B2: =1+($A$2/100) -> 1.01 | C2: 1.0411645 | E2: Source | F2: https://aspe.hhs.gov/sites/default/files/documents/cd2a1348ea0777b1aa918089e4965b8c/standard-ria-values.pdf
E3: Citation | F3: Consumer Product Safety Commission (CPSC) 2024 Notice of Availability of Final Guidance for Estimating Value per Statistical Life Fed. Regist. Online: https://www.federalregister.gov/documents/2024/04/18/2024-08300/notice-of-availability-of-final-guidance-for-estimating-value-per-statistical-life

Sheet vsl_adjustment_factor
A1: year | B1: epa_vsl_usd2022 | C1: cpi_ratio_2023_2022 | D1: income_elasticity | E1: epa_vsl_usd2023 | F1: vsl_adjustment_factor
A2: 2023 | B2: =CPSC_VSL_Guidance!$C$2 -> 11 | C2: =CPSC_HHS_VSL_Guidelines!$C$2 -> 1.0411645 | D2: =CPSC_HHS_VSL_Guidelines!$B$2 -> 1.01 | E2: =(B2*C2)*D2^(A2-$A$2) -> 11.45281 | F2: =E2/$E$3 -> 0.99009901
A3: 2024 | B3: =CPSC_VSL_Guidance!$C$2 -> 11 | C3: =CPSC_HHS_VSL_Guidelines!$C$2 -> 1.0411645 | D3: =CPSC_HHS_VSL_Guidelines!$B$2 -> 1.01 | E3: =(B3*C3)*D3^(A3-$A$2) -> 11.567338 | F3: =E3/$E$3 -> 1
A4: 2025 | B4: =CPSC_VSL_Guidance!$C$2 -> 11 | C4: =CPSC_HHS_VSL_Guidelines!$C$2 -> 1.0411645 | D4: =CPSC_HHS_VSL_Guidelines!$B$2 -> 1.01 | E4: =(B4*C4)*D4^(A4-$A$2) -> 11.683011 | F4: =E4/$E$3 -> 1.01
A5: 2026 | B5: =CPSC_VSL_Guidance!$C$2 -> 11 | C5: =CPSC_HHS_VSL_Guidelines!$C$2 -> 1.0411645 | D5: =CPSC_HHS_VSL_Guidelines!$B$2 -> 1.01 | E5: =(B5*C5)*D5^(A5-$A$2) -> 11.799841 | F5: =E5/$E$3 -> 1.0201
A6: 2027 | B6: =CPSC_VSL_Guidance!$C$2 -> 11 | C6: =CPSC_HHS_VSL_Guidelines!$C$2 -> 1.0411645 | D6: =CPSC_HHS_VSL_Guidelines!$B$2 -> 1.01 | E6: =(B6*C6)*D6^(A6-$A$2) -> 11.91784 | F6: =E6/$E$3 -> 1.030301
A7: 2028 | B7: =CPSC_VSL_Guidance!$C$2 -> 11 | C7: =CPSC_HHS_VSL_Guidelines!$C$2 -> 1.0411645 | D7: =CPSC_HHS_VSL_Guidelines!$B$2 -> 1.01 | E7: =(B7*C7)*D7^(A7-$A$2) -> 12.037018 | F7: =E7/$E$3 -> 1.040604
A8: 2029 | B8: =CPSC_VSL_Guidance!$C$2 -> 11 | C8: =CPSC_HHS_VSL_Guidelines!$C$2 -> 1.0411645 | D8: =CPSC_HHS_VSL_Guidelines!$B$2 -> 1.01 | E8: =(B8*C8)*D8^(A8-$A$2) -> 12.157388 | F8: =E8/$E$3 -> 1.0510101
A9: 2030 | B9: =CPSC_VSL_Guidance!$C$2 -> 11 | C9: =CPSC_HHS_VSL_Guidelines!$C$2 -> 1.0411645 | D9: =CPSC_HHS_VSL_Guidelines!$B$2 -> 1.01 | E9: =(B9*C9)*D9^(A9-$A$2) -> 12.278962 | F9: =E9/$E$3 -> 1.0615202
A10: 2031 | B10: =CPSC_VSL_Guidance!$C$2 -> 11 | C10: =CPSC_HHS_VSL_Guidelines!$C$2 -> 1.0411645 | D10: =CPSC_HHS_VSL_Guidelines!$B$2 -> 1.01 | E10: =(B10*C10)*D10^(A10-$A$2) -> 12.401752 | F10: =E10/$E$3 -> 1.0721354
A11: 2032 | B11: =CPSC_VSL_Guidance!$C$2 -> 11 | C11: =CPSC_HHS_VSL_Guidelines!$C$2 -> 1.0411645 | D11: =CPSC_HHS_VSL_Guidelines!$B$2 -> 1.01 | E11: =(B11*C11)*D11^(A11-$A$2) -> 12.525769 | F11: =E11/$E$3 -> 1.0828567
A12: 2033 | B12: =CPSC_VSL_Guidance!$C$2 -> 11 | C12: =CPSC_HHS_VSL_Guidelines!$C$2 -> 1.0411645 | D12: =CPSC_HHS_VSL_Guidelines!$B$2 -> 1.01 | E12: =(B12*C12)*D12^(A12-$A$2) -> 12.651027 | F12: =E12/$E$3 -> 1.0936853
A13: 2034 | B13: =CPSC_VSL_Guidance!$C$2 -> 11 | C13: =CPSC_HHS_VSL_Guidelines!$C$2 -> 1.0411645 | D13: =CPSC_HHS_VSL_Guidelines!$B$2 -> 1.01 | E13: =(B13*C13)*D13^(A13-$A$2) -> 12.777537 | F13: =E13/$E$3 -> 1.1046221
... A29: 2050 | B29: =CPSC_VSL_Guidance!$C$2 -> 11 | C29: =CPSC_HHS_VSL_Guidelines!$C$2 -> 1.0411645 | D29: =CPSC_HHS_VSL_Guidelines!$B$2 -> 1.01 | E29: =(B29*C29)*D29^(A29-$A$2) -> 14.982667 | F29: =E29/$E$3 -> 1.2952563
